odoo9_addon_website_google_tag_manager-9.0.1.0.0-py2.7-nspkg.pth
odoo_addons/website_google_tag_manager/__openerp__.py
odoo_addons/website_google_tag_manager/__init__.py
odoo_addons/website_google_tag_manager/README.rst
odoo_addons/website_google_tag_manager/models/website_config_settings.py
odoo_addons/website_google_tag_manager/models/__init__.py
odoo_addons/website_google_tag_manager/models/website.py
odoo_addons/website_google_tag_manager/views/website.xml
odoo_addons/website_google_tag_manager/views/templates.xml
odoo_addons/website_google_tag_manager/views/website_config_settings.xml
odoo_addons/website_google_tag_manager/static/description/icon.svg
odoo_addons/website_google_tag_manager/static/description/image.png
odoo9_addon_website_google_tag_manager-9.0.1.0.0.dist-info/top_level.txt
odoo9_addon_website_google_tag_manager-9.0.1.0.0.dist-info/WHEEL
odoo9_addon_website_google_tag_manager-9.0.1.0.0.dist-info/RECORD
odoo9_addon_website_google_tag_manager-9.0.1.0.0.dist-info/metadata.json
odoo9_addon_website_google_tag_manager-9.0.1.0.0.dist-info/DESCRIPTION.rst
odoo9_addon_website_google_tag_manager-9.0.1.0.0.dist-info/METADATA
odoo9_addon_website_google_tag_manager-9.0.1.0.0.dist-info/namespace_packages.txt
